odoo10_addon_mail_improved_tracking_value-10.0.1.0.1-py3.8-nspkg.pth
odoo/addons/mail_improved_tracking_value/README.rst
odoo/addons/mail_improved_tracking_value/__init__.py
odoo/addons/mail_improved_tracking_value/__manifest__.py
odoo/addons/mail_improved_tracking_value/i18n/mail_improved_tracking_value.pot
odoo/addons/mail_improved_tracking_value/models/__init__.py
odoo/addons/mail_improved_tracking_value/models/mail_tracking_value.py
odoo/addons/mail_improved_tracking_value/static/description/icon.png
odoo/addons/mail_improved_tracking_value/tests/__init__.py
odoo/addons/mail_improved_tracking_value/tests/test_improved_tracking_value.py
odoo/addons/mail_improved_tracking_value/views/mail_tracking_value.xml
odoo10_addon_mail_improved_tracking_value-10.0.1.0.1.dist-info/METADATA
odoo10_addon_mail_improved_tracking_value-10.0.1.0.1.dist-info/WHEEL
odoo10_addon_mail_improved_tracking_value-10.0.1.0.1.dist-info/namespace_packages.txt
odoo10_addon_mail_improved_tracking_value-10.0.1.0.1.dist-info/top_level.txt
odoo10_addon_mail_improved_tracking_value-10.0.1.0.1.dist-info/RECORD
